JarvisPackage/init.py
jarvispackage-0.1.dist-info/METADATA
jarvispackage-0.1.dist-info/WHEEL
jarvispackage-0.1.dist-info/top_level.txt
jarvispackage-0.1.dist-info/RECORD
